{
  "id": "T006",
  "index": 6,
  "title": "二、本月檢查存在問題及整改建議",
  "policy_context": "年 月至 月安全施工計劃 > 一、本月檢查整改情況 > 二、本月檢查存在問題及整改建議",
  "nearby_paragraphs": [
    "地盤名稱： 填表日期： / /",
    "附件1.4",
    "年 月",
    "安全施工計劃自檢報告",
    "年 月安全施工計劃自檢報告",
    "地盤名稱： 填表日期：20 / /",
    "一、本月檢查整改情況",
    "二、本月檢查存在問題及整改建議"
  ],
  "rows": 8,
  "columns": 5,
  "non_empty_cell_count": 27,
  "first_row": [
    "序號",
    "本月不安全事項",
    "整改建議",
    "整改責任人",
    "整改責任人"
  ],
  "headers_guess": [
    "序號",
    "本月不安全事項",
    "整改建議",
    "整改責任人",
    "整改責任人"
  ],
  "docx_path": "E:\\China Oversea  Final\\safety-policy-templates-20241025\\tables-docx\\T006_二、本月檢查存在問題及整改建議.docx",
  "json_path": "E:\\China Oversea  Final\\safety-policy-templates-20241025\\tables-json\\T006_二、本月檢查存在問題及整改建議.json",
  "markdown_path": "E:\\China Oversea  Final\\safety-policy-templates-20241025\\tables-md\\T006_二、本月檢查存在問題及整改建議.md",
  "cells": [
    [
      "序號",
      "本月不安全事項",
      "整改建議",
      "整改責任人",
      "整改責任人"
    ],
    [
      "序號",
      "本月不安全事項",
      "整改建議",
      "姓名",
      "職位"
    ],
    [
      "1",
      "相片",
      "1. 2. 3. …",
      "",
      ""
    ],
    [
      "1",
      "文字描述",
      "1. 2. 3. …",
      "",
      ""
    ],
    [
      "2",
      "相片",
      "1. 2. 3. …",
      "",
      ""
    ],
    [
      "2",
      "文字描述",
      "1. 2. 3. …",
      "",
      ""
    ],
    [
      "3",
      "相片",
      "1. 2. 3. …",
      "",
      ""
    ],
    [
      "3",
      "文字描述",
      "",
      "",
      ""
    ]
  ],
  "source": "c:\\Users\\User\\Desktop\\安全管理辦法彙編20241025（無修訂版）.docx"
}